UzSyllable/UzSyllable.py
UzSyllable/__init__.py
UzSyllable-0.0.8.dist-info/LICENSE
UzSyllable-0.0.8.dist-info/METADATA
UzSyllable-0.0.8.dist-info/WHEEL
UzSyllable-0.0.8.dist-info/top_level.txt
UzSyllable-0.0.8.dist-info/RECORD
