Metadata-Version: 2.1
Name: UzSyllable
Version: 0.0.8
Summary: UzSyllable | The Syllable Separator, Line breaks and Counter for Uzbek Language
Home-page: https://github.com/UlugbekSalaev/UzSyllable
Author: Ulugbek Salaev
Author-email: ulugbek0302@gmail.com
Project-URL: Bug Tracker, https://github.com/UlugbekSalaev/UzSyllable/issues
Keywords: syllable,hyphenation,uzbek-language
Classifier: Programming Language :: Python :: 3
Classifier: License :: OSI Approved :: MIT License
Classifier: Operating System :: OS Independent
Requires-Python: >=3.6
License-File: LICENSE
